Simba_UW_no_tf-1.3.0.dist-info/METADATA
Simba_UW_no_tf-1.3.0.dist-info/RECORD
Simba_UW_no_tf-1.3.0.dist-info/WHEEL
Simba_UW_no_tf-1.3.0.dist-info/entry_points.txt
Simba_UW_no_tf-1.3.0.dist-info/top_level.txt
simba/FSTCC.py
simba/Kleinberg_burst_analysis.py
simba/ROI_add_to_features.py
simba/ROI_add_to_features_old.py
simba/ROI_add_to_features_old2.py
simba/ROI_add_to_features_old3.py
simba/ROI_analysis.py
simba/ROI_analysis_2.py
simba/ROI_analysis_old.py
simba/ROI_directionality_to_other_animals.py
simba/ROI_directionality_to_other_animals_visualize.py
simba/ROI_draw_defined.py
simba/ROI_freehand_draw_3.py
simba/ROI_multiply.py
simba/ROI_plot.py
simba/ROI_plot_multi_process.py
simba/ROI_plot_old.py
simba/ROI_plot_old_2.py
simba/ROI_process_movement.py
simba/ROI_process_movement_old.py
simba/ROI_process_movement_old2.py
simba/ROI_reset.py
simba/ROI_visualize_features.py
simba/SimBA.py
simba/SimBA_040921.py
simba/SimBA_dash_app.py
simba/SimBA_logo.ico
simba/SimBA_smidm.py
simba/TheGoldenLab.PNG
simba/TheGoldenLab_aboutme.png
simba/__init__.py
simba/appendMars.py
simba/append_boris.py
simba/append_boris_old.py
simba/classifierValidation.py
simba/correct_devs_loc.py
simba/correct_devs_mov.py
simba/create_project_ini.py
simba/crop_video_tool_user_bounding_box_multiple.py
simba/data_plot.py
simba/define_new_pose_config.py
simba/dlc_change_yamlfile.py
simba/dpk_create_project_ini.py
simba/drop_bp_cords.py
simba/extract_frames_fast.py
simba/extract_seqframes.py
simba/ez_lineplot.py
simba/gantt.py
simba/gantt_old.py
simba/gantt_video.py
simba/get_coordinates_tools_v2.py
simba/golden.png
simba/import_sleap_h5.py
simba/import_solomon.py
simba/import_videos_csv_project_ini.py
simba/json2csv.py
simba/labelling_aggression.py
simba/line_plot.py
simba/load_labelling_aggression.py
simba/load_labelling_aggression_hxt.py
simba/merge_frames.py
simba/merge_frames_movie.py
simba/merge_frames_movie_old.py
simba/merge_frames_movie_old_2.py
simba/merge_movie_ffmpeg.py
simba/multiplecrop.py
simba/path_plot.py
simba/path_plot_new.py
simba/play_video.py
simba/play_video_pseudo.py
simba/plot_heatmap.py
