Metadata-Version: 2.1
Name: Simba-UW-no-tf
Version: 1.3.0
Summary: Toolkit for computer classification of complex social behaviors in experimental animals
Home-page: https://github.com/sgoldenlab/simba
Author: Simon Nilsson, Jia Jie Choong, Sophia Hwang, Sam Golden
Author-email: goldenneurolab@gmail.com
License: GNU Lesser General Public License v3 (LGPLv3)
Platform: UNKNOWN
Classifier: Programming Language :: Python :: 3
Classifier: License :: OSI Approved :: GNU Lesser General Public License v3 (LGPLv3)
Classifier: Operating System :: OS Independent
Requires-Dist: Pillow (==5.4.1)
Requires-Dist: pyyaml (==5.3.1)
Requires-Dist: shapely (==1.7)
Requires-Dist: wxpython (==4.0.4)
Requires-Dist: dtreeviz (==0.8.1)
Requires-Dist: eli5 (==0.10.1)
Requires-Dist: graphviz (==0.11)
Requires-Dist: imblearn (==0.0)
Requires-Dist: imgaug (==0.4.0)
Requires-Dist: imutils (==0.5.2)
Requires-Dist: matplotlib (==3.0.3)
Requires-Dist: numpy (==1.18.1)
Requires-Dist: opencv-python (==3.4.5.20)
Requires-Dist: pandas (==0.25.3)
Requires-Dist: scikit-image (==0.14.2)
Requires-Dist: scipy (==1.1.0)
Requires-Dist: seaborn (==0.9.0)
Requires-Dist: scikit-learn (==0.22.2)
Requires-Dist: tabulate (==0.8.3)
Requires-Dist: tqdm (==4.30.0)
Requires-Dist: xgboost (==0.90)
Requires-Dist: yellowbrick (==0.9.1)
Requires-Dist: dash (==1.14.0)
Requires-Dist: dash-color-picker (==0.0.1)
Requires-Dist: dash-core-components (==1.10.2)
Requires-Dist: dash-colorscales (==0.0.4)
Requires-Dist: dash-html-components (==1.0.3)
Requires-Dist: h5py (==2.9.0)
Requires-Dist: numba (==0.48.0)
Requires-Dist: numexpr (==2.6.9)
Requires-Dist: plotly (==4.9.0)
Requires-Dist: statsmodels (==0.9.0)
Requires-Dist: cefpython3 (==66.0)
Requires-Dist: pyarrow (==0.17.1)
Requires-Dist: shap (==0.35.0)
Requires-Dist: h5py (==2.9.0)
